shadow_tasks/__init__.py
shadow_tasks/apps.py
shadow_tasks/mixins.py
shadow_tasks/registry.py
shadow_tasks/routing.py
shadow_tasks/schema.py
shadow_tasks/settings.py
shadow_tasks/structs.py
shadow_tasks/utils.py
shadow_tasks/consuming/__init__.py
shadow_tasks/consuming/cli_start.py
shadow_tasks/consuming/consumer.py
shadow_tasks/consuming/task_executor.py
shadow_tasks/publishing/__init__.py
shadow_tasks/publishing/publisher.py
django_shadow_tasks-0.0.6.dist-info/METADATA
django_shadow_tasks-0.0.6.dist-info/WHEEL
django_shadow_tasks-0.0.6.dist-info/entry_points.txt
django_shadow_tasks-0.0.6.dist-info/top_level.txt
django_shadow_tasks-0.0.6.dist-info/RECORD
