Metadata-Version: 2.1
Name: django-shadow-tasks
Version: 0.0.6
Summary: Run tasks in background workers
Home-page: https://git.supl.biz/web-back-tools/django-shadow-tasks
Author: Supl.biz
Author-email: tech@supl.biz
License: UNKNOWN
Platform: UNKNOWN
Classifier: Programming Language :: Python :: 3.7
Classifier: License :: OSI Approved :: MIT License
Requires-Dist: django (>=2.1)
Requires-Dist: pika (==1.1.0)
